duplicated_image_cleaner/__init__.py
duplicated_image_cleaner-0.2.1.dist-info/METADATA
duplicated_image_cleaner-0.2.1.dist-info/WHEEL
duplicated_image_cleaner-0.2.1.dist-info/entry_points.txt
duplicated_image_cleaner-0.2.1.dist-info/top_level.txt
duplicated_image_cleaner-0.2.1.dist-info/RECORD
